sdTranslate/__init__.py
sdTranslate/main.py
sdTranslate-0.3.dist-info/METADATA
sdTranslate-0.3.dist-info/WHEEL
sdTranslate-0.3.dist-info/top_level.txt
sdTranslate-0.3.dist-info/RECORD
