Metadata-Version: 2.1
Name: sdTranslate
Version: 0.3
Summary: A description of sdTranslate
Home-page: https://github.com/yourusername/sdTranslate
Author: Siraj_Dal
Author-email: write2sirajv@gmail.com
Classifier: Programming Language :: Python :: 3
Classifier: License :: OSI Approved :: MIT License
Classifier: Operating System :: OS Independent
Requires-Python: >=3.6
Requires-Dist: requests
Requires-Dist: unidecode
